liju_mcp_demo/__init__.py
liju_mcp_demo-0.1.0.dist-info/METADATA
liju_mcp_demo-0.1.0.dist-info/WHEEL
liju_mcp_demo-0.1.0.dist-info/entry_points.txt
liju_mcp_demo-0.1.0.dist-info/RECORD
