Metadata-Version: 2.4
Name: liju-mcp-demo
Version: 0.1.0
Summary: Add your description here
Author-email: luliju <luliju@kanzhun.com>
Requires-Python: >=3.11
Requires-Dist: mcp[cli]>=1.9.4
